{"stats":{"minecraft:used":{"minecraft:lever":1,"minecraft:donkey_spawn_egg":61,"minecraft:sand":3,"minecraft:creeper_head":1,"minecraft:waxed_copper_bulb":2,"minecraft:tnt":154},"minecraft:custom":{"minecraft:jump":25,"minecraft:time_since_rest":550,"minecraft:deaths":1,"minecraft:play_time":6029,"minecraft:leave_game":2,"minecraft:sprint_one_cm":2789,"minecraft:time_since_death":492,"minecraft:walk_one_cm":3544,"minecraft:sneak_time":81,"minecraft:total_world_time":6029,"minecraft:drop":24,"minecraft:fly_one_cm":84129},"minecraft:picked_up":{"minecraft:sand":88,"minecraft:creeper_head":1,"minecraft:gunpowder":6},"minecraft:dropped":{"minecraft:sand":24}},"DataVersion":3955}